exp_converter/__init__.py
exp_converter/converter.py
expression_converter/__init__.py
expression_converter/converter.py
exp_converter-0.1.0.dist-info/METADATA
exp_converter-0.1.0.dist-info/WHEEL
exp_converter-0.1.0.dist-info/top_level.txt
exp_converter-0.1.0.dist-info/RECORD
